plotly_calheatmap/__init__.py
plotly_calheatmap/calendar_calheatmap.py
plotly_calheatmap/calheatmap.py
plotly_calheatmap/colorscale_utils.py
plotly_calheatmap/date_extractors.py
plotly_calheatmap/hourly_calheatmap.py
plotly_calheatmap/i18n.py
plotly_calheatmap/layout_formatter.py
plotly_calheatmap/raw_heatmap.py
plotly_calheatmap/single_year_calheatmap.py
plotly_calheatmap/utils.py
plotly_calheatmap-0.5.dist-info/LICENSE
plotly_calheatmap-0.5.dist-info/METADATA
plotly_calheatmap-0.5.dist-info/WHEEL
plotly_calheatmap-0.5.dist-info/RECORD
