Metadata-Version: 2.1
Name: plotly_calheatmap
Version: 0.5
Summary: Calendar Plot made with Plotly
Home-page: https://github.com/thomazyujibaba/plotly-calheatmap
License: MIT
Author: Bruno Rodrigues Silva
Author-email: b.rosilva1@gmail.com
Requires-Python: >=3.10,<4.0.0
Classifier: License :: OSI Approved :: MIT License
Classifier: Programming Language :: Python :: 3
Classifier: Programming Language :: Python :: 3.10
Classifier: Programming Language :: Python :: 3.11
Classifier: Programming Language :: Python :: 3.12
Classifier: Programming Language :: Python :: 3.13
Requires-Dist: babel (>=2.10.0)
Requires-Dist: numpy (>=1.24.0)
Requires-Dist: pandas
Requires-Dist: plotly (>=5.4.0)
Requires-Dist: pytz
Project-URL: Repository, https://github.com/thomazyujibaba/plotly-calheatmap
